immage/__init__.py
immage/generate_texture.py
immage/immage.py
immage-1.1.4.dist-info/LICENSE
immage-1.1.4.dist-info/METADATA
immage-1.1.4.dist-info/WHEEL
immage-1.1.4.dist-info/top_level.txt
immage-1.1.4.dist-info/RECORD
