Metadata-Version: 2.1
Name: immage
Version: 1.1.4
Summary: A versatile image processing library with method chaining and procedural texture generation.
Home-page: https://github.com/sq5rix/immage
Author: Tom Wawer
Author-email: sq5rix@gmail.com
Classifier: Programming Language :: Python :: 3
Classifier: License :: OSI Approved :: MIT License
Classifier: Operating System :: OS Independent
License-File: LICENSE
Requires-Dist: Pillow
Requires-Dist: numpy
Requires-Dist: noise
